finkl/__init__.py
finkl/monoid.py
finkl/util.py
finkl/abc/__init__.py
finkl/abc/eq.py
finkl/abc/functor.py
finkl/abc/monad.py
finkl/abc/monoid.py
finkl/monad/__init__.py
finkl/monad/list.py
finkl/monad/maybe.py
finkl/monad/writer.py
test/__init__.py
test/test_list.py
test/test_maybe.py
test/test_monoid.py
test/test_writer.py
finkl-0.0.4.dist-info/LICENSE
finkl-0.0.4.dist-info/METADATA
finkl-0.0.4.dist-info/WHEEL
finkl-0.0.4.dist-info/top_level.txt
finkl-0.0.4.dist-info/RECORD
