Metadata-Version: 2.1
Name: finkl
Version: 0.0.4
Summary: Haskell's algebraic primitives reimplemented in Python
Home-page: https://github.com/Xophmeister/finkl
Author: Christopher Harrison
Author-email: pypi@acc.xoph.co
License: GPLv3
Platform: any
Requires-Python: >=3.7
License-File: LICENSE
